enguard/__init__.py
enguard/configs.py
enguard/configs/__init__.py
enguard/configs/base.py
enguard/configs/image_classification.py
enguard/configs/image_text_to_text.py
enguard/configs/text_classification.py
enguard/configs/token_classification.py
enguard/configs/utils.py
enguard/guardrails/__init__.py
enguard/guardrails/base.py
enguard/guardrails/image_classification.py
enguard/guardrails/image_text_to_text.py
enguard/guardrails/text_classification.py
enguard/guardrails/text_generation.py
enguard/guardrails/token_classification.py
strike-0.0.1.dist-info/licenses/LICENSE.txt
strike-0.0.1.dist-info/METADATA
strike-0.0.1.dist-info/WHEEL
strike-0.0.1.dist-info/top_level.txt
strike-0.0.1.dist-info/RECORD
